ucam_wls/__init__.py
ucam_wls/context.py
ucam_wls/errors.py
ucam_wls/request.py
ucam_wls/response.py
ucam_wls/signing.py
ucam_wls/status.py
ucam_wls/util.py
ucam_wls-0.0.2.dist-info/COPYING
ucam_wls-0.0.2.dist-info/METADATA
ucam_wls-0.0.2.dist-info/WHEEL
ucam_wls-0.0.2.dist-info/top_level.txt
ucam_wls-0.0.2.dist-info/RECORD
