Metadata-Version: 2.1
Name: ucam-wls
Version: 0.0.2
Summary: A web login service library for the Ucam-WebAuth (WAA2WLS) protocol
Home-page: https://github.com/edwinbalani/ucam-wls
Author: Edwin Bahrami Balani
Author-email: eb677@srcf.net
License: MIT
Keywords: cambridge university raven login authentication waa2wls ucam webauth ucam-webauth wls
Platform: UNKNOWN
Classifier: Programming Language :: Python :: 3
Classifier: Development Status :: 2 - Pre-Alpha
Classifier: License :: OSI Approved :: MIT License
Classifier: Intended Audience :: Developers
Classifier: Intended Audience :: System Administrators
Classifier: Topic :: Internet :: WWW/HTTP
Classifier: Topic :: Security
Classifier: Topic :: Software Development :: Libraries
Classifier: Topic :: System :: Systems Administration :: Authentication/Directory
Requires-Python: >=3
Requires-Dist: cryptography
